water5py/__init__.py
water5py/__main__.py
water5py/command.py
water5py/daily.py
water5py/decode.py
water5py/info.py
water5py/reset.py
water5py/type_massage.py
water5py/utils.py
water5py/weekly.py
ul_water5py-2.0.1.dist-info/LICENSE
ul_water5py-2.0.1.dist-info/METADATA
ul_water5py-2.0.1.dist-info/WHEEL
ul_water5py-2.0.1.dist-info/top_level.txt
ul_water5py-2.0.1.dist-info/RECORD
